burro/__init__.py
burro/run.py
burro/agents/__init__.py
burro/agents/agent.py
burro/agents/categorical_agent.py
burro/agents/refill_agent.py
burro/games/__init__.py
burro/games/beer_game.py
burro/games/markov_game.py
burro/policies/__init__.py
burro/policies/base_policy.py
burro/policies/categorical_policy.py
burro/processes/__init__.py
burro/processes/discrete_point_process.py
burro/processes/hawkes_process.py
burro/processes/poisson_process.py
burro/util/__init__.py
burro/util/calc.py
burro/util/colors.py
burro/util/ext_torch.py
burro/util/nn.py
burro/util/sampling.py
burro/util/type_checking.py
burrolib-0.1.1.dist-info/LICENSE.md
burrolib-0.1.1.dist-info/METADATA
burrolib-0.1.1.dist-info/WHEEL
burrolib-0.1.1.dist-info/top_level.txt
burrolib-0.1.1.dist-info/RECORD
