Metadata-Version: 2.1
Name: burrolib
Version: 0.1.1
Summary: burro - a supply chain simulator
Home-page: https://github.com/kosmitive/burro
Author: xploras
Author-email: dev@xploras.net
License: UNKNOWN
Platform: UNKNOWN
Classifier: Programming Language :: Python :: 3
Classifier: License :: OSI Approved :: MIT License
Classifier: Operating System :: OS Independent
Requires-Python: >=3.7
Requires-Dist: matplotlib
Requires-Dist: numpy
Requires-Dist: torch
Requires-Dist: typing
